ioxplugin/__init__.py
ioxplugin/ast_util.py
ioxplugin/commands.py
ioxplugin/create_launch_env.sh
ioxplugin/editor.py
ioxplugin/iox_controller_template.py
ioxplugin/iox_main_template.py
ioxplugin/iox_node_gen.py
ioxplugin/iox_profile.py
ioxplugin/iox_transport.py
ioxplugin/log.py
ioxplugin/main_gen.py
ioxplugin/new_project.py
ioxplugin/node_properties.py
ioxplugin/nodedef.py
ioxplugin/oauth_service.py
ioxplugin/plugin.py
ioxplugin/plugin_meta.py
ioxplugin/properties.py
ioxplugin/protocol.py
ioxplugin/store_ops.py
ioxplugin/uom.py
ioxplugin/validator.py
ioxplugin-1.5.6.dist-info/licenses/LICENSE
tests/__init__.py
tests/sampleProtocolHandler.py
tests/test_ioxplugin.py
tests/version.py
ioxplugin-1.5.6.dist-info/METADATA
ioxplugin-1.5.6.dist-info/WHEEL
ioxplugin-1.5.6.dist-info/top_level.txt
ioxplugin-1.5.6.dist-info/RECORD
